sensirion_i2c_scd/__init__.py
sensirion_i2c_scd/version.py
sensirion_i2c_scd/scd4x/__init__.py
sensirion_i2c_scd/scd4x/commands.py
sensirion_i2c_scd/scd4x/data_types.py
sensirion_i2c_scd/scd4x/device.py
sensirion_i2c_scd/scd4x/response_types.py
sensirion_i2c_scd-0.1.2.dist-info/LICENSE
sensirion_i2c_scd-0.1.2.dist-info/METADATA
sensirion_i2c_scd-0.1.2.dist-info/WHEEL
sensirion_i2c_scd-0.1.2.dist-info/top_level.txt
sensirion_i2c_scd-0.1.2.dist-info/RECORD
